[
  {
    "question": "'क' को गुजराती में कैसे लिखा जाता है?",
    "choices": ["ક", "ભ", "ળ", "ઞ"],
    "answer": "ક",
    "explanation": "'ક' is the Gujarati equivalent of Devanagari 'क' (velar consonant)",
    "audio": "q1.mp3"
  },
  {
    "question": "'ख' को गुजराती में कैसे लिखा जाता है?",
    "choices": ["છ", "ખ", "ધ", "ષ"],
    "answer": "ખ",
    "explanation": "'ખ' is the Gujarati equivalent of Devanagari 'ख' (aspirated velar)",
    "audio": "q2.mp3"
  },
  {
    "question": "'ग' को गुजराती में कैसे लिखा जाता है?",
    "choices": ["ગ", "દ", "ઝ", "એ"],
    "answer": "ગ",
    "explanation": "'ગ' is the Gujarati equivalent of Devanagari 'ग' (voiced velar)",
    "audio": "q3.mp3"
  },
  {
    "question": "'घ' को गुजराती में कैसे लिखा जाता है?",
    "choices": ["ઘ", "ઙ", "થ", "શ"],
    "answer": "ઘ",
    "explanation": "'ઘ' is the Gujarati equivalent of Devanagari 'घ' (voiced aspirated velar)",
    "audio": "q4.mp3"
  },
  {
    "question": "'च' को गुजराती में कैसे लिखा जाता है?",
    "choices": ["ચ", "ડ", "ણ", "હ"],
    "answer": "ચ",
    "explanation": "'ચ' is the Gujarati equivalent of Devanagari 'च' (palatal consonant)",
    "audio": "q5.mp3"
  },
  {
    "question": "'छ' को गुजराती में कैसे लिखा जाता है?",
    "choices": ["છ", "ય", "ઘ", "ફ"],
    "answer": "છ",
    "explanation": "'છ' is the Gujarati equivalent of Devanagari 'छ' (aspirated palatal)",
    "audio": "q6.mp3"
  },
  {
    "question": "'ज' को गुजराती में कैसे लिखा जाता है?",
    "choices": ["જ", "ઓ", "ઠ", "ળ"],
    "answer": "જ",
    "explanation": "'જ' is the Gujarati equivalent of Devanagari 'ज' (voiced palatal)",
    "audio": "q7.mp3"
  },
  {
    "question": "'झ' को गुजराती में कैसे लिखा जाता है?",
    "choices": ["ઝ", "ઢ", "ન", "ર"],
    "answer": "ઝ",
    "explanation": "'ઝ' is the Gujarati equivalent of Devanagari 'झ' (voiced aspirated palatal)",
    "audio": "q8.mp3"
  },
  {
    "question": "'ट' को गुजराती में कैसे लिखा जाता है?",
    "choices": ["ટ", "ત", "મ", "ઔ"],
    "answer": "ટ",
    "explanation": "'ટ' is the Gujarati equivalent of Devanagari 'ट' (retroflex consonant)",
    "audio": "q9.mp3"
  },
  {
    "question": "'ठ' को गुजराती में कैसे लिखा जाता है?",
    "choices": ["ઠ", "આ", "ભ", "ઞ"],
    "answer": "ઠ",
    "explanation": "'ઠ' is the Gujarati equivalent of Devanagari 'ठ' (aspirated retroflex)",
    "audio": "q10.mp3"
  },
  {
    "question": "'ड' को गुजराती में कैसे लिखा जाता है?",
    "choices": ["ડ", "ઈ", "ષ", "છ"],
    "answer": "ડ",
    "explanation": "'ડ' is the Gujarati equivalent of Devanagari 'ड' (voiced retroflex)",
    "audio": "q11.mp3"
  },
  {
    "question": "'ढ' को गुजराती में कैसे लिखा जाता है?",
    "choices": ["ઢ", "ઊ", "જ", "દ"],
    "answer": "ઢ",
    "explanation": "'ઢ' is the Gujarati equivalent of Devanagari 'ढ' (voiced aspirated retroflex)",
    "audio": "q12.mp3"
  },
  {
    "question": "'त' को गुजराती में कैसे लिखा जाता है?",
    "choices": ["ત", "એ", "ગ", "ય"],
    "answer": "ત",
    "explanation": "'ત' is the Gujarati equivalent of Devanagari 'त' (dental consonant)",
    "audio": "q13.mp3"
  },
  {
    "question": "'थ' को गुजराती में कैसे लिखा जाता है?",
    "choices": ["થ", "ઑ", "ટ", "વ"],
    "answer": "થ",
    "explanation": "'થ' is the Gujarati equivalent of Devanagari 'थ' (aspirated dental)",
    "audio": "q14.mp3"
  },
  {
    "question": "'द' को गुजराती में कैसे लिखा जाता है?",
    "choices": ["દ", "ણ", "ક", "સ"],
    "answer": "દ",
    "explanation": "'દ' is the Gujarati equivalent of Devanagari 'द' (voiced dental)",
    "audio": "q15.mp3"
  },
  {
    "question": "'ध' को गुजराती में कैसे लिखा जाता है?",
    "choices": ["ધ", "ઋ", "છ", "પ"],
    "answer": "ધ",
    "explanation": "'ધ' is the Gujarati equivalent of Devanagari 'ध' (voiced aspirated dental)",
    "audio": "q16.mp3"
  },
  {
    "question": "'प' को गुजराती में कैसे लिखा जाता है?",
    "choices": ["પ", "ઍ", "ઢ", "ઙ"],
    "answer": "પ",
    "explanation": "'પ' is the Gujarati equivalent of Devanagari 'प' (labial consonant)",
    "audio": "q17.mp3"
  },
  {
    "question": "'फ' को गुजराती में कैसे लिखा जाता है?",
    "choices": ["ફ", "ઐ", "ઠ", "ઘ"],
    "answer": "ફ",
    "explanation": "'ફ' is the Gujarati equivalent of Devanagari 'फ' (aspirated labial)",
    "audio": "q18.mp3"
  },
  {
    "question": "'ब' को गुजराती में कैसे लिखा जाता है?",
    "choices": ["બ", "ઓ", "થ", "ળ"],
    "answer": "બ",
    "explanation": "'બ' is the Gujarati equivalent of Devanagari 'ब' (voiced labial)",
    "audio": "q19.mp3"
  },
  {
    "question": "'भ' को गुजराती में कैसे लिखा जाता है?",
    "choices": ["ભ", "ઔ", "દ", "ઞ"],
    "answer": "ભ",
    "explanation": "'ભ' is the Gujarati equivalent of Devanagari 'भ' (voiced aspirated labial)",
    "audio": "q20.mp3"
  },
  {
    "question": "'य' को गुजराती में कैसे लिखा जाता है?",
    "choices": ["ય", "ા", "ષ", "ઙ"],
    "answer": "ય",
    "explanation": "'ય' is the Gujarati equivalent of Devanagari 'य' (palatal approximant)",
    "audio": "q21.mp3"
  },
  {
    "question": "'र' को गुजराती में कैसे लिखा जाता है?",
    "choices": ["ર", "ી", "હ", "ઘ"],
    "answer": "ર",
    "explanation": "'ર' is the Gujarati equivalent of Devanagari 'र' (alveolar trill)",
    "audio": "q22.mp3"
  },
  {
    "question": "'ल' को गुजराती में कैसे लिखा जाता है?",
    "choices": ["લ", "ુ", "ફ", "ચ"],
    "answer": "લ",
    "explanation": "'લ' is the Gujarati equivalent of Devanagari 'ल' (dental lateral approximant)",
    "audio": "q23.mp3"
  },
  {
    "question": "'व' को गुजराती में कैसे लिखा जाता है?",
    "choices": ["વ", "ૂ", "ટ", "છ"],
    "answer": "વ",
    "explanation": "'વ' is the Gujarati equivalent of Devanagari 'व' (labio-dental approximant)",
    "audio": "q24.mp3"
  },
  {
    "question": "'श' को गुजराती में कैसे लिखा जाता है?",
    "choices": ["શ", "ે", "ડ", "ખ"],
    "answer": "શ",
    "explanation": "'શ' is the Gujarati equivalent of Devanagari 'श' (palatal fricative)",
    "audio": "q25.mp3"
  },
  {
    "question": "'ष' को गुजराती में कैसे लिखा जाता है?",
    "choices": ["ષ", "ૈ", "ણ", "ગ"],
    "answer": "ષ",
    "explanation": "'ષ' is the Gujarati equivalent of Devanagari 'ष' (retroflex fricative)",
    "audio": "q26.mp3"
  },
  {
    "question": "'स' को गुजराती में कैसे लिखा जाता है?",
    "choices": ["સ", "ો", "ઢ", "ભ"],
    "answer": "સ",
    "explanation": "'સ' is the Gujarati equivalent of Devanagari 'स' (dental fricative)",
    "audio": "q27.mp3"
  },
  {
    "question": "'ह' को गुजराती में कैसे लिखा जाता है?",
    "choices": ["હ", "ૌ", "ધ", "ય"],
    "answer": "હ",
    "explanation": "'હ' is the Gujarati equivalent of Devanagari 'ह' (glottal fricative)",
    "audio": "q28.mp3"
  },
  {
    "question": "'ड़' को गुजराती में कैसे लिखा जाता है?",
    "choices": ["ડ", "ં", "ળ", "ઞ"],
    "answer": "ડ",
    "explanation": "In Gujarati, 'ડ' represents both 'ड' and 'ड़' sounds",
    "audio": "q29.mp3"
  },
  {
    "question": "'ढ़' को गुजराती में कैसे लिखा जाता है?",
    "choices": ["ઢ", "ઃ", "ષ", "ણ"],
    "answer": "ઢ",
    "explanation": "In Gujarati, 'ઢ' represents both 'ढ' and 'ढ़' sounds",
    "audio": "q30.mp3"
  },
  {
    "question": "'ञ' को गुजराती में कैसे लिखा जाता है?",
    "choices": ["ઞ", "્", "ઙ", "જ"],
    "answer": "ઞ",
    "explanation": "'ઞ' is the Gujarati equivalent of Devanagari 'ञ' (palatal nasal)",
    "audio": "q31.mp3"
  },
  {
    "question": "'ण' को गुजराती में कैसे लिखा जाता है?",
    "choices": ["ણ", "ઋ", "ન", "છ"],
    "answer": "ણ",
    "explanation": "'ણ' is the Gujarati equivalent of Devanagari 'ण' (retroflex nasal)",
    "audio": "q32.mp3"
  },
  {
    "question": "'न' को गुजराती में कैसे लिखा जाता है?",
    "choices": ["ન", "ૠ", "મ", "ઘ"],
    "answer": "ન",
    "explanation": "'ન' is the Gujarati equivalent of Devanagari 'न' (dental nasal)",
    "audio": "q33.mp3"
  },
  {
    "question": "'म' को गुजराती में कैसे लिखा जाता है?",
    "choices": ["મ", "ઍ", "બ", "થ"],
    "answer": "મ",
    "explanation": "'મ' is the Gujarati equivalent of Devanagari 'म' (labial nasal)",
    "audio": "q34.mp3"
  },
  {
    "question": "'ङ' को गुजराती में कैसे लिखा जाता है?",
    "choices": ["ઙ", "ઑ", "ય", "દ"],
    "answer": "ઙ",
    "explanation": "'ઙ' is the Gujarati equivalent of Devanagari 'ङ' (velar nasal)",
    "audio": "q35.mp3"
  },
  {
    "question": "'ळ' को गुजराती में कैसे लिखा जाता है?",
    "choices": ["ળ", "એ", "વ", "ઠ"],
    "answer": "ળ",
    "explanation": "'ળ' is a special retroflex lateral in Gujarati with no exact Hindi equivalent",
    "audio": "q36.mp3"
  }
]
